attendify/__init__.py
attendify/attendance.py
attendify/cli.py
attendify/exceptions.py
attendify/parser.py
attendify/rules.py
attendify/timetable.py
attendify-0.1.1.dist-info/METADATA
attendify-0.1.1.dist-info/WHEEL
attendify-0.1.1.dist-info/entry_points.txt
attendify-0.1.1.dist-info/top_level.txt
attendify-0.1.1.dist-info/RECORD
