Metadata-Version: 2.4
Name: attendify
Version: 0.1.1
Summary: CLI tool to analyze attendance risk from CSV files
Author: Sanyam Bhansali
License: MIT
Requires-Python: >=3.10
